MANIFEST.in
README.md
setup.cfg
setup.py
serverboards/__init__.py
serverboards/async.py
serverboards/sync.py
serverboards.egg-info/PKG-INFO
serverboards.egg-info/SOURCES.txt
serverboards.egg-info/dependency_links.txt
serverboards.egg-info/requires.txt
serverboards.egg-info/top_level.txt