Metadata-Version: 1.1
Name: serverboards
Version: 18.4b1
Summary: Serverboards python bindings
Home-page: https://github.com/serverboards/serverboards/
Author: David Moreno
Author-email: dmoreno@serverboards.io
License: UNKNOWN
Keywords: serverboards dashboard json rpc bindings async sync
Platform: UNKNOWN
Classifier: Development Status :: 4 - Beta
Classifier: Intended Audience :: Developers
Classifier: Topic :: Software Development :: Build Tools
Classifier: License :: OSI Approved :: Apache Software License
Classifier: Programming Language :: Python :: 3.5
Classifier: Programming Language :: Python :: 3.6
